pandera_sampler/__init__.py
pandera_sampler/pandera_sampler.py
pandera_sampler-0.0.5.dist-info/METADATA
pandera_sampler-0.0.5.dist-info/WHEEL
pandera_sampler-0.0.5.dist-info/top_level.txt
pandera_sampler-0.0.5.dist-info/RECORD
