Metadata-Version: 2.1
Name: pandera-sampler
Version: 0.0.5
Summary: A compact package to enhance ML development.
Project-URL: Homepage, https://github.com/pypa/samplesproject
Project-URL: Bug Tracker, https://github.com/pypa/sampleproject/issues
Classifier: Programming Language :: Python :: 3
Classifier: License :: OSI Approved :: MIT License
Classifier: Operating System :: OS Independent
Requires-Python: >=3.10
Requires-Dist: pandera >=0.16.1
Requires-Dist: pandas >=1.5.0
Requires-Dist: numpy >=1.20.1
